{"Starting Position":"Center","Commands":[{"Params":[6000.0],"Command Name":"goToHeight","Subsystem Name":"Elevator"},{"Params":[358.2581551023069,2.0,1.0,10.0],"Command Name":"turnToAngle","Subsystem Name":"Drive"},{"Params":[1.6937305684404105,4.0,1.0,1.0],"Command Name":"driveDistance","Subsystem Name":"Drive"},{"Commands":[{"Params":[307.8749836510982,3.1904761904761902,1.0,15.714285714285714],"Command Name":"turnToAngle","Subsystem Name":"Drive"},{"Params":[6.413486766182651,5.952380952380952,1.0,1.4581061975844751],"Command Name":"driveDistance","Subsystem Name":"Drive"},{"Params":[13000.0],"Command Name":"goToHeight","Subsystem Name":"Elevator"},{"Params":[0.0,3.071428571428571,1.0,20.0],"Command Name":"turnToAngle","Subsystem Name":"Drive"},{"Params":[2.25,4.0,1.0,1.0],"Command Name":"driveDistance","Subsystem Name":"Drive"},{"Params":[0.45],"Command Name":"shoot","Subsystem Name":"Intake"},{"Params":[0.9240453527727084,2.0,1.0,10.0],"Command Name":"turnToAngle","Subsystem Name":"Drive"},{"Params":[-4.982790856476695,4.0,1.0,1.0],"Command Name":"driveDistance","Subsystem Name":"Drive"}],"Conditional":"leftSwitchOurs"},{"Commands":[{"Params":[49.89909245378777,3.1904761904761902,1.0,15.714285714285714],"Command Name":"turnToAngle","Subsystem Name":"Drive"},{"Params":[5.988090060823286,5.904761904761903,1.0,1.475245242922483],"Command Name":"driveDistance","Subsystem Name":"Drive"},{"Params":[13000.0],"Command Name":"goToHeight","Subsystem Name":"Elevator"},{"Params":[1.9749340108819926,3.3095238095238093,1.0,20.0],"Command Name":"turnToAngle","Subsystem Name":"Drive"},{"Params":[2.331742199230754,4.0,1.0,1.0],"Command Name":"driveDistance","Subsystem Name":"Drive"},{"Params":[0.45],"Command Name":"shoot","Subsystem Name":"Intake"},{"Params":[0.0,2.0,1.0,10.0],"Command Name":"turnToAngle","Subsystem Name":"Drive"},{"Params":[-3.8571428571428577,4.0,1.0,1.0],"Command Name":"driveDistance","Subsystem Name":"Drive"}],"Conditional":"rightSwitchOurs"}]}